libtsm/__init__.py
libtsm/pitchshift.py
libtsm/tsm.py
libtsm/utils.py
libtsm-1.1.2.dist-info/LICENSE
libtsm-1.1.2.dist-info/METADATA
libtsm-1.1.2.dist-info/WHEEL
libtsm-1.1.2.dist-info/top_level.txt
libtsm-1.1.2.dist-info/RECORD
