Metadata-Version: 2.1
Name: libtsm
Version: 1.1.2
Summary: Python Package for Time-Scale Modification and Pitch-Shifting
Home-page: https://www.audiolabs-erlangen.de/resources/MIR/2021-DAFX-AdaptivePitchShifting
Download-URL: https://github.com/meinardmueller/libtsm/archive/refs/tags/v1.1.2.tar.gz
Author: Sebastian Rosenzweig, Simon Schwär, Jonathan Driedger and Meinard Müller
Author-email: sebastian.rosenzweig@audiolabs-erlangen.de
License: MIT
Keywords: audio,music,tsm,pitch-shifting
Classifier: License :: OSI Approved :: MIT License
Classifier: Programming Language :: Python
Classifier: Intended Audience :: Developers
Classifier: Topic :: Multimedia :: Sound/Audio :: Analysis
Classifier: Programming Language :: Python :: 3
Requires-Python: >=3.6
License-File: LICENSE
Requires-Dist: numpy>=1.17.0
Requires-Dist: scipy>=1.3.0
Provides-Extra: dev
Requires-Dist: ipython>=7.8.0; extra == "dev"
Requires-Dist: jupyter==1.0.*; extra == "dev"
Requires-Dist: librosa>=0.8.0; extra == "dev"
Requires-Dist: nbstripout==0.4.*; extra == "dev"
Requires-Dist: matplotlib>=3.1.0; extra == "dev"
Provides-Extra: test
Requires-Dist: pytest==6.2.*; extra == "test"
Requires-Dist: soundfile>=0.9.0; extra == "test"
Provides-Extra: docs
Requires-Dist: sphinx==4.0.*; extra == "docs"
Requires-Dist: sphinx-rtd-theme==0.5.*; extra == "docs"
